ezdxf/__init__.py
ezdxf/__main__.py
ezdxf/_options.py
ezdxf/appsettings.py
ezdxf/audit.py
ezdxf/bbox.py
ezdxf/blkrefs.py
ezdxf/colors.py
ezdxf/commands.py
ezdxf/comments.py
ezdxf/disassemble.py
ezdxf/document.py
ezdxf/dwginfo.py
ezdxf/dynblkhelper.py
ezdxf/edgeminer.py
ezdxf/edgesmith.py
ezdxf/entitydb.py
ezdxf/enums.py
ezdxf/explode.py
ezdxf/eztypes.py
ezdxf/filemanagement.py
ezdxf/gfxattribs.py
ezdxf/graphicsfactory.py
ezdxf/groupby.py
ezdxf/messenger.py
ezdxf/msgtypes.py
ezdxf/npshapes.py
ezdxf/protocols.py
ezdxf/proxygraphic.py
ezdxf/py.typed
ezdxf/query.py
ezdxf/queryparser.py
ezdxf/r12strict.py
ezdxf/recover.py
ezdxf/reorder.py
ezdxf/revcloud.py
ezdxf/select.py
ezdxf/transform.py
ezdxf/units.py
ezdxf/upright.py
ezdxf/urecord.py
ezdxf/version.py
ezdxf/xclip.py
ezdxf/xref.py
ezdxf/zoom.py
ezdxf/acc/__init__.py
ezdxf/acc/bezier3p.c
ezdxf/acc/bezier3p.cp314-win_amd64.pyd
ezdxf/acc/bezier3p.pyx
ezdxf/acc/bezier4p.c
ezdxf/acc/bezier4p.cp314-win_amd64.pyd
ezdxf/acc/bezier4p.pyx
ezdxf/acc/bspline.c
ezdxf/acc/bspline.cp314-win_amd64.pyd
ezdxf/acc/bspline.pyx
ezdxf/acc/constants.h
ezdxf/acc/construct.c
ezdxf/acc/construct.cp314-win_amd64.pyd
ezdxf/acc/construct.pyx
ezdxf/acc/linetypes.c
ezdxf/acc/linetypes.cp314-win_amd64.pyd
ezdxf/acc/linetypes.pyx
ezdxf/acc/mapbox_earcut.c
ezdxf/acc/mapbox_earcut.cp314-win_amd64.pyd
ezdxf/acc/mapbox_earcut.pyx
ezdxf/acc/matrix44.c
ezdxf/acc/matrix44.cp314-win_amd64.pyd
ezdxf/acc/matrix44.pxd
ezdxf/acc/matrix44.pyx
ezdxf/acc/np_support.c
ezdxf/acc/np_support.cp314-win_amd64.pyd
ezdxf/acc/np_support.pyx
ezdxf/acc/vector.c
ezdxf/acc/vector.cp314-win_amd64.pyd
ezdxf/acc/vector.pxd
ezdxf/acc/vector.pyx
ezdxf/acis/__init__.py
ezdxf/acis/abstract.py
ezdxf/acis/api.py
ezdxf/acis/cache.py
ezdxf/acis/const.py
ezdxf/acis/dbg.py
ezdxf/acis/dxf.py
ezdxf/acis/entities.py
ezdxf/acis/hdr.py
ezdxf/acis/mesh.py
ezdxf/acis/sab.py
ezdxf/acis/sat.py
ezdxf/acis/type_hints.py
ezdxf/addons/__init__.py
ezdxf/addons/acadctb.py
ezdxf/addons/binpacking.py
li_ezdxf-1.4.4.dist-info/licenses/LICENSE
li_ezdxf-1.4.4.dist-info/METADATA
li_ezdxf-1.4.4.dist-info/WHEEL
li_ezdxf-1.4.4.dist-info/entry_points.txt
li_ezdxf-1.4.4.dist-info/top_level.txt
li_ezdxf-1.4.4.dist-info/RECORD
