Metadata-Version: 2.4
Name: li-ezdxf
Version: 1.4.4
Summary: A Python package to create/manipulate DXF drawings.
Author-email: Manfred Moitzi <me@mozman.at>
Project-URL: Repository, https://github.com/mozman/ezdxf
Project-URL: Documentation, https://ezdxf.readthedocs.io
Project-URL: Changelog, https://ezdxf.mozman.at/notes/#/page/changelog
Project-URL: Forum, https://github.com/mozman/ezdxf/discussions
Project-URL: Issues, https://github.com/mozman/ezdxf/issues
Project-URL: Website, https://ezdxf.mozman.at
Project-URL: Download, https://pypi.org/project/ezdxf
Keywords: DXF,CAD
Classifier: Development Status :: 5 - Production/Stable
Classifier: License :: OSI Approved :: MIT License
Classifier: Operating System :: OS Independent
Classifier: Programming Language :: Python :: 3
Classifier: Programming Language :: Python :: 3.10
Classifier: Programming Language :: Python :: 3.11
Classifier: Programming Language :: Python :: 3.12
Classifier: Programming Language :: Python :: 3.13
Classifier: Programming Language :: Python :: 3.14
Classifier: Programming Language :: Python :: Implementation :: CPython
Classifier: Programming Language :: Python :: Implementation :: PyPy
Classifier: Intended Audience :: Developers
Classifier: Topic :: Software Development :: Libraries :: Python Modules
Classifier: Typing :: Typed
Provides: ezdxf
Requires-Python: >=3.10
License-File: LICENSE
Requires-Dist: pyparsing>=2.0.1
Requires-Dist: typing_extensions>=4.6.0
Requires-Dist: numpy
Requires-Dist: fonttools
Provides-Extra: draw
Requires-Dist: PySide6; extra == "draw"
Requires-Dist: matplotlib; extra == "draw"
Requires-Dist: PyMuPDF>=1.20.0; extra == "draw"
Requires-Dist: Pillow; extra == "draw"
Provides-Extra: draw5
Requires-Dist: PyQt5; extra == "draw5"
Requires-Dist: matplotlib; extra == "draw5"
Requires-Dist: PyMuPDF>=1.20.0; extra == "draw5"
Requires-Dist: Pillow; extra == "draw5"
Provides-Extra: dev
Requires-Dist: PySide6; extra == "dev"
Requires-Dist: setuptools; extra == "dev"
Requires-Dist: wheel; extra == "dev"
Requires-Dist: Cython; extra == "dev"
Requires-Dist: pytest; extra == "dev"
Requires-Dist: Pillow; extra == "dev"
Requires-Dist: matplotlib; extra == "dev"
Requires-Dist: PyMuPDF>=1.20.0; extra == "dev"
Provides-Extra: dev5
Requires-Dist: PyQt5; extra == "dev5"
Requires-Dist: setuptools; extra == "dev5"
Requires-Dist: wheel; extra == "dev5"
Requires-Dist: Cython; extra == "dev5"
Requires-Dist: pytest; extra == "dev5"
Requires-Dist: Pillow; extra == "dev5"
Requires-Dist: matplotlib; extra == "dev5"
Requires-Dist: PyMuPDF>=1.20.0; extra == "dev5"
Dynamic: license-file
